brute_force_cython_ext.cpython-310-x86_64-linux-gnu.so
imagededup/__init__.py
imagededup/evaluation/__init__.py
imagededup/evaluation/evaluation.py
imagededup/handlers/__init__.py
imagededup/handlers/metrics/__init__.py
imagededup/handlers/metrics/classification.py
imagededup/handlers/metrics/information_retrieval.py
imagededup/handlers/search/__init__.py
imagededup/handlers/search/bktree.py
imagededup/handlers/search/brute_force.py
imagededup/handlers/search/brute_force_cython.py
imagededup/handlers/search/retrieval.py
imagededup/methods/__init__.py
imagededup/methods/cnn.py
imagededup/methods/hashing.py
imagededup/utils/__init__.py
imagededup/utils/data_generator.py
imagededup/utils/general_utils.py
imagededup/utils/image_utils.py
imagededup/utils/logger.py
imagededup/utils/models.py
imagededup/utils/plotter.py
kakaimagededup/__init__.py
kakaimagededup/evaluation/__init__.py
kakaimagededup/evaluation/evaluation.py
kakaimagededup/handlers/__init__.py
kakaimagededup/handlers/metrics/__init__.py
kakaimagededup/handlers/metrics/classification.py
kakaimagededup/handlers/metrics/information_retrieval.py
kakaimagededup/handlers/search/__init__.py
kakaimagededup/handlers/search/bktree.py
kakaimagededup/handlers/search/brute_force.py
kakaimagededup/handlers/search/brute_force_cython.py
kakaimagededup/handlers/search/hash_block.py
kakaimagededup/handlers/search/retrieval.py
kakaimagededup/methods/__init__.py
kakaimagededup/methods/cnn.py
kakaimagededup/methods/hashing.py
kakaimagededup/utils/__init__.py
kakaimagededup/utils/data_generator.py
kakaimagededup/utils/general_utils.py
kakaimagededup/utils/image_utils.py
kakaimagededup/utils/logger.py
kakaimagededup/utils/models.py
kakaimagededup/utils/plotter.py
kakaimagededup-0.3.9.dist-info/LICENSE
kakaimagededup-0.3.9.dist-info/METADATA
kakaimagededup-0.3.9.dist-info/WHEEL
kakaimagededup-0.3.9.dist-info/top_level.txt
kakaimagededup-0.3.9.dist-info/RECORD
